pypigit/__init__.py
pypigit/handler.py
pypigit/repos.py
pypigit/server.py
pypigit/templates/package_versions.html
pypigit/templates/simple_index.html
pypigit-0.2.8.dist-info/METADATA
pypigit-0.2.8.dist-info/WHEEL
pypigit-0.2.8.dist-info/top_level.txt
pypigit-0.2.8.dist-info/RECORD
